happyrs-0.1.0.dist-info/METADATA
happyrs-0.1.0.dist-info/WHEEL
librust/__init__.py
librust/librust.cpython-39-darwin.so
happyrs-0.1.0.dist-info/RECORD
